classic/operations/__init__.py
classic/operations/callbacks.py
classic/operations/decorator.py
classic/operations/operation.py
classic_operations-0.3.1.dist-info/LICENSE
classic_operations-0.3.1.dist-info/METADATA
classic_operations-0.3.1.dist-info/WHEEL
classic_operations-0.3.1.dist-info/top_level.txt
classic_operations-0.3.1.dist-info/RECORD
