Metadata-Version: 2.1
Name: classic-operations
Version: 0.3.1
Summary: Provides primitives for transactional application logic
Home-page: https://github.com/variasov/classic-operations
Author: Sergei Variasov
Author-email: variasov@gmail.com
Project-URL: Bug Tracker, https://github.com/variasov/classic-operations/issues
Classifier: Programming Language :: Python :: 3.10
Classifier: License :: OSI Approved :: MIT License
Classifier: Operating System :: OS Independent
Classifier: Development Status :: 4 - Beta
Requires-Python: >=3.10
License-File: LICENSE
Requires-Dist: classic-components~=1.2
Provides-Extra: dev
Requires-Dist: pytest~=7.4.4; extra == "dev"
Requires-Dist: pytest-cov~=4.1; extra == "dev"
Requires-Dist: twine~=4.0; extra == "dev"
Requires-Dist: build~=1.0; extra == "dev"
